{
    "cameraGrain": 0.0,
    "motionQuality": 0.0,
    "projectionMatrix": [
        1.658347249031067,
        0.0,
        0.004694640636444092,
        0.0,
        0.0,
        2.211129665374756,
        0.007722377777099609,
        0.0,
        0.0,
        0.0,
        -0.9999997615814209,
        -0.0009999998146668077,
        0.0,
        0.0,
        -1.0,
        0.0
    ],
    "convertedProjectionMatrix": {
        "e00": 0.0,
        "e01": 0.0,
        "e02": 0.0,
        "e03": 0.0,
        "e10": 0.0,
        "e11": 0.0,
        "e12": 0.0,
        "e13": 0.0,
        "e20": 0.0,
        "e21": 0.0,
        "e22": 0.0,
        "e23": 0.0,
        "e30": 0.0,
        "e31": 0.0,
        "e32": 0.0,
        "e33": 0.0
    },
    "intrinsics": [
        0.0,
        0.0,
        0.0,
        0.0,
        0.0,
        0.0,
        0.0,
        0.0,
        0.0
    ],
    "focalLength": {
        "x": 0.0,
        "y": 0.0
    },
    "principalPoint": {
        "x": 0.0,
        "y": 0.0
    },
    "averageVelocity": 0.0,
    "frame_index": 0,
    "time": 0.0,
    "averageAngularVelocity": 0.0,
    "exposureDuration": 0.0,
    "cameraPoseARFrame": [
        -0.05284622684121132,
        -0.9728949069976807,
        -0.22512836754322053,
        0.018640711903572084,
        -0.8902481198310852,
        -0.056234005838632587,
        0.4519912302494049,
        -0.2728775143623352,
        -0.4523998200893402,
        0.224306121468544,
        -0.8631460666656494,
        -0.00964813306927681,
        0.0,
        0.0,
        0.0,
        1.0
    ],
    "convertedCameraPoseARFrame": {
        "e00": 0.0,
        "e01": 0.05284622684121132,
        "e02": 0.22512836754322053,
        "e03": 0.0,
        "e10": 0.0,
        "e11": 0.8902481198310852,
        "e12": -0.4519912302494049,
        "e13": 0.0,
        "e20": 0.0,
        "e21": 0.4523998200893402,
        "e22": 0.8631460666656494,
        "e23": 0.0,
        "e30": 0.0,
        "e31": 0.0,
        "e32": 0.0,
        "e33": 0.0
    },
    "url": "",
    "capture": {
        "m_FileID": -158,
        "m_PathID": 0
    }
}