{
    "cameraGrain": 0.0,
    "motionQuality": 0.0,
    "projectionMatrix": [
        1.6569349765777588,
        0.0,
        0.005145370960235596,
        0.0,
        0.0,
        2.2092466354370119,
        0.008006274700164795,
        0.0,
        0.0,
        0.0,
        -0.9999997615814209,
        -0.0009999998146668077,
        0.0,
        0.0,
        -1.0,
        0.0
    ],
    "convertedProjectionMatrix": {
        "e00": 0.0,
        "e01": 0.0,
        "e02": 0.0,
        "e03": 0.0,
        "e10": 0.0,
        "e11": 0.0,
        "e12": 0.0,
        "e13": 0.0,
        "e20": 0.0,
        "e21": 0.0,
        "e22": 0.0,
        "e23": 0.0,
        "e30": 0.0,
        "e31": 0.0,
        "e32": 0.0,
        "e33": 0.0
    },
    "intrinsics": [
        0.0,
        0.0,
        0.0,
        0.0,
        0.0,
        0.0,
        0.0,
        0.0,
        0.0
    ],
    "focalLength": {
        "x": 0.0,
        "y": 0.0
    },
    "principalPoint": {
        "x": 0.0,
        "y": 0.0
    },
    "averageVelocity": 0.0,
    "frame_index": 0,
    "time": 0.0,
    "averageAngularVelocity": 0.0,
    "exposureDuration": 0.0,
    "cameraPoseARFrame": {
        "e00": -0.8904926776885986,
        "e01": 0.26201197504997256,
        "e02": 0.3719847500324249,
        "e03": 0.1105516329407692,
        "e10": -0.06746521592140198,
        "e11": 0.7324808835983276,
        "e12": -0.6774364709854126,
        "e13": -0.19251902401447297,
        "e20": -0.4499681890010834,
        "e21": -0.6283482313156128,
        "e22": -0.6345921754837036,
        "e23": 0.7948043942451477,
        "e30": 0.0,
        "e31": 0.0,
        "e32": 0.0,
        "e33": 1.0
    },
    "url": "",
    "capture": {
        "m_FileID": -17968,
        "m_PathID": 0
    }
}